.clangd.in
.dvcignore
.gitignore
.pre-commit-config.yaml
.pylintrc
CMakeLists.txt
LICENSE
MANIFEST.in
README.md
debug_script.py
multiline.json
noxfile.py
pyproject.toml
setup.cfg
setup.py
.devcontainer/Dockerfile
.devcontainer/devcontainer.json
.dvc/.gitignore
.dvc/config
.dvc/plots/multiline.json
.github/dependabot.yml
.github/workflows/conda.yml
.github/workflows/pip.yml
.github/workflows/publish-to-test-pypi.yml
.github/workflows/wheels.yml
benchmarks/.gitignore
benchmarks/benchmark.py
benchmarks/machine_log.py
benchmarks/params_schema.json
benchmarks/requirements.txt
benchmarks/run_all_DPU_benchmarks.sh
benchmarks/run_all_GPU_benchmarks.sh
benchmarks/setup_gpu_env.sh
benchmarks/dimension/CPU+DPU.py
benchmarks/dimension/CPU.py
benchmarks/dimension/DPU.py
benchmarks/dimension/benchmarks.csv
benchmarks/dimension/dvc.lock
benchmarks/dimension/dvc.yaml
benchmarks/dimension/machine.yaml
benchmarks/dimension/metrics.json
benchmarks/dimension/params.yaml
benchmarks/dimension/plots.csv
benchmarks/dropin_patch/__init__.py
benchmarks/dropin_patch/_kmeans_w_perf.py
benchmarks/dropin_patch/readme.md
benchmarks/higgs/.gitignore
benchmarks/higgs/CPU+DPU.py
benchmarks/higgs/DPU_profiling.py
benchmarks/higgs/GPU.py
benchmarks/higgs/benchmarks.csv
benchmarks/higgs/dvc.lock
benchmarks/higgs/dvc.yaml
benchmarks/higgs/machine.yaml
benchmarks/higgs/metrics.json
benchmarks/higgs/params.yaml
benchmarks/higgs/plots.csv
benchmarks/higgs/data/convert_to_pq.py
benchmarks/higgs_big/benchmarks.csv
benchmarks/higgs_big/dvc.lock
benchmarks/higgs_big/dvc.yaml
benchmarks/higgs_big/machine.yaml
benchmarks/higgs_big/metrics.json
benchmarks/higgs_big/params.yaml
benchmarks/higgs_big/plots.csv
benchmarks/higgs_big/data/.gitkeep
benchmarks/precision/CPU+DPU.py
benchmarks/precision/benchmarks.csv
benchmarks/precision/dvc.lock
benchmarks/precision/dvc.yaml
benchmarks/precision/machine.yaml
benchmarks/precision/metrics.json
benchmarks/precision/params.yaml
benchmarks/precision/plots.csv
src/dpu_kmeans.egg-info/PKG-INFO
src/dpu_kmeans.egg-info/SOURCES.txt
src/dpu_kmeans.egg-info/dependency_links.txt
src/dpu_kmeans.egg-info/not-zip-safe
src/dpu_kmeans.egg-info/requires.txt
src/dpu_kmeans.egg-info/top_level.txt
