Metadata-Version: 2.1
Name: dpu-kmeans
Version: 0.1.8
Summary: A package for the k-means algorithm on DPU.
Home-page: https://github.com/upmem/dpu_kmeans
Author: Sylvan Brocard
Author-email: sylvan.brocard@gmail.com
License: MIT
Platform: UNKNOWN
Provides-Extra: test
Provides-Extra: benchmarks
License-File: LICENSE
